[
  {
    "id": "4ac90730-29ab-436b-92b0-54e54a8869a0",
    "name": "PRO X TKL",
    "description": "Teclado inalámbrico para juegos: interruptores mecánicos",
    "price": 239.99,
    "images": [
      "/PR_02/assets/img/keyboard.png",
      "/PR_02/assets/img/keyboard2.png",
      "/PR_02/assets/img/keyboard3.png"
    ],
    "colors": ["Black", "White"]
  },
  {
    "id": "f81e16f6-9f53-408d-b792-b2a3228b4108",
    "name": "PRO X SL 2 DEX",
    "description": "Ratón gaming ergonómico con alta precisión.",
    "price": 159.99,
    "images": [
      "/PR_02/assets/img/mouse.png",
      "/PR_02/assets/img/mouse2.png",
      "/PR_02/assets/img/mouse3.png"
    ],
    "colors": ["Black", "White"]
  },
  {
    "id": "d2df5222-00fd-49e5-9817-f7252935649c",
    "name": "PRO X WL",
    "description": "Auriculares inalámbricos para juegos 7.1 LIGHTSPEED",
    "price": 239.99,
    "images": [
      "/PR_02/assets/img/headset.png",
      "/PR_02/assets/img/headset2.png",
      "/PR_02/assets/img/headset3.png"
    ],
    "colors": ["Black", "White"]
  },
  {
    "id": "c7a27ad1-cef6-414a-9439-24b49068c770",
    "name": "PRO RACING WHEEL",
    "description": "Volante de simulación para juegos de carreras realistas.",
    "price": 549.99,
    "images": [
      "/PR_02/assets/img/wheel.png",
      "/PR_02/assets/img/wheel2.png",
      "/PR_02/assets/img/wheel3.png"
    ],
    "colors": ["Black"]
  }
]